helperModules.v
module invert(input wire i, output wire o1);
	assign o1 = !i;
endmodule

module and2(input wire i0, i1, output wire o2);
	assign o2 = i0 & i1;
endmodule

module and3(input wire i0, i1, i2, output wire o6);
	assign o6 = i0 & i1 & i2;
endmodule

module or2(input wire i0, i1, output wire o3);
	assign o3 = i0 | i1;
endmodule

module xor2_v2(input wire i0, i1, output wire o3);
	assign o3 = ( i0 & (!i1) ) | ( i1 & (!i0) );
endmodule

module xor2(input wire i0, i1, output wire o4);
	assign o4 = i0 ^ i1;
endmodule

module xor3(input wire i0, i1, i2, output wire o7);
	assign o7 = i0 ^ i1 ^ i2;
endmodule

module xor3E(input wire i0, i1, i2, output wire o7);
	assign o7 = ( !i0 & !i1 & i2 ) | ( !i0 & i1 & !i2 ) | ( i0 & !i1 & !i2 );// | ( i0 & i1 & i2 );
endmodule

module or3(input wire i0, i1, i2, output wire o4);
	assign o4 = i0 | i1 | i2;
endmodule

module nand2(input wire i0, i1, output wire o5);
	wire t;
	and2 and2_0 (i0, i1, t);
	invert invert_0 (t, o5);
endmodule

prefixAdder.v
module and_or2(input wire a, b, c, x, y, output wire d, e);
	and2 and2_d(a, b, t);
	or2 or2_d(t, c, d);
	and2 and2_e(x, y, e);
endmodule

module prefixAdder(
input [7:0] a,
input [7:0] b,
output [8:0] sum
);
	wire [15:0] p;
	wire [15:0] g;
	wire [15:0] cp1;
	wire [15:0] cg1;
	wire cp22;
	wire cg22;
	wire cp23;
	wire cg23;
	wire cp27;
	wire cg27;
	wire cp34;
	wire cg34;
	wire cp35;
	wire cg35;
	wire cp36;
	wire cg36;
	wire cp37;
	wire cg37;
	wire cp211;
	wire cg211;
	wire cp215;
	wire cg215;
	wire cp315;
	wire cg315;
	wire cp411;
	wire cg411;
	wire cp415;
	wire cg415;
	wire cp59;
	wire cg59;
	wire cp513;
	wire cg513;

	wire [8:0] s;
	// start fist level
	xor2 xor2_p0(a[0], b[0], p[0]);

	and2 a2(a[0], b[0], g[0]); //assign g[0] = a[0] & b[0];
	assign cp1[0] = p[0];
	assign cg1[0] = g[0]; //first level zero bit complete

	xor2 xor2_p1(a[1], b[1], p[1]); // assign p[1] = a[1] ^ b[1]; //first level first bit start
	and2 and2_g1(a[1], b[1], g[1]); // assign g[1] = a[1] & b[1];
	and_or2 and_or_cg1_1(p[1], g[0], g[1], p[1], g[0], cg1[1], cp1[1]); // first level first bit complete

	xor2 xor2_p2(a[2], b[2], p[2]); // assign p[2] = a[2] ^ b[2]; //first level 2nd bit start
	and2 and2_g2(a[2], b[2], g[2]); // assign g[2] = a[2] & b[2];
	assign cp1[2] = p[2];
	assign cg1[2] = g[2]; // first level 2nd bit complete

	xor2 xor2_p3(a[3], b[3], p[3]); //first level 3rd bit start
	and2 and2_g3(a[3], b[3], g[3]); 
	and_or2 and_or_cg1_3(p[3], g[2], g[3], p[3], p[2], cg1[3], cp1[3]); 
	//first level 3rd bit complete

	xor2 xpr2_p4(a[4], b[4], p[4]); 
	and2 and2_g4(a[4], b[4], g[4]);
	assign cg1[4] = g[4];
	assign cp1[4] = p[4];

	xor2 xor2_p5(a[5], b[5], p[5]); 
	and2 and2_g5(a[5], b[5], g[5]); 
	and_or2 and_or_cg1_5(p[5], g[4], g[5], p[5], p[4], cg1[5], cp1[5]);

	xor2 xor2_p6(a[6], b[6], p[6]);
	and2 and2_g6(a[6], b[6], g[6]);
	assign cg1[6] = g[6];
	assign cp1[6] = p[6];

	xor2 xor2_p7(a[7], b[7], p[7]);
	and2 and2_g7(a[7], b[7], g[7]); 
	and_or2 and_or_cg1_7(p[7], g[6], g[7], p[7], p[6], cg1[7], cp1[7]); 

	and_or2 and_or_cg2_2(cp1[2], cg1[1], cg1[2], cp1[2], cp1[1], cg22, cp22);
	and_or2 and_or_cg2_3(cp1[3], cg1[1], cg1[3], cp1[3], cp1[1], cg23, cp23);

	and_or2 and_or_cg2_7(cp1[7], cg1[5], cg1[7], cp1[7], cp1[5], cg27, cp27);

	and_or2 and_or_cg3_4(cp1[4], cg23, cg1[4], cp1[4], cp23, cg34, cp34); 

	and_or2 and_or_cg3_5(cp1[5], cg23, cg1[5], cp1[5], cp23, cg35, cp35); 

	and_or2 and_or_cg3_6(cp1[6], cg35, cg1[6], cp1[6], cp35, cg36, cp36);
	and_or2 and_or_cg3_7(cp27,   cg23, cg27,   cp27,   cp23, cg37, cp37);

	and_or2 and_or_cg2_11(cp1[11], cg1[9], cg1[11], cp1[11], cp1[9], cg211, cp211);

	and_or2 and_or_cg2_15(cp1[15], cg1[11], cg1[15], cp1[15], cp1[11], cg215, cp215);

	and_or2 and_or_cg3_15(cp215, cg211, cg215, cp215, cp211, cg315, cp315);

	and_or2 and_or_cg4_11(cp211, cg37, cg211, cp211, cp37, cg411, cp411);

	and_or2 and_or_cg4_15(cp315, cg37, cg315, cp315, cp37, cg415, cp415);

	and_or2 and_or_cg5_9(cp1[9], cg37, cg1[9], cp1[9], cp37 , cg59, cp59);

	and_or2 and_or_cg5_13(cp1[13], cg411, cg1[13], cp1[13], cp411, cg513, cp513);


	assign s[0] = p[0];
	xor2 xor2_s1(p[1], cg1[0], s[1]); 
	xor2 xor2_s2(p[2], cg1[1], s[2]); 
	xor2 xor2_s3(p[3], cg22, s[3]); 
	xor2 xor2_s4(p[4], cg23, s[4]); 
	xor2 xor2_s5(p[5], cg34, s[5]); 
	xor2 xor2_s6(p[6], cg35, s[6]); 
	xor2 xor2_s7(p[7], cg36, s[7]); 
	assign s[8] =  cg37;

	assign sum = {s[8:0]};

endmodule

testBench.v
`timescale 1 ns / 100 ps
`define TESTVECS 8

module tb;
  reg clk, reset;
  reg [7:0] i0, i1;
  wire [8:0] o; wire cout;
  reg [31:0] test_vecs [0:(`TESTVECS-1)];
  integer i;
  initial begin $dumpfile("prefixAdder.vcd"); $dumpvars(0,tb); end
  initial begin reset = 1'b1; #12.5 reset = 1'b0; end
  initial clk = 1'b0; always #5 clk =~ clk;
  initial begin
  	//test_vecs[0][33:32] = 2'b00; test_vecs[0][31:8] = 16'h00;test_vecs[0][15:0] = 16'h00;
    
    test_vecs[0][15:8] = 16'b01;  test_vecs[0][7:0] = 16'b00;
    test_vecs[1][15:8] = 16'b01;  test_vecs[1][7:0] = 16'b01;
    test_vecs[2][15:8] = 16'hff;  test_vecs[2][7:0] = 16'b01;
    test_vecs[3][15:8] = 16'hff;  test_vecs[3][7:0] = 16'hff;
    test_vecs[4][15:8] = 16'haf;  test_vecs[4][7:0] = 16'hfa;
    test_vecs[5][15:8] = 16'hf1;  test_vecs[5][7:0] = 16'hf9;
    test_vecs[6][15:8] = 16'hcc;  test_vecs[6][7:0] = 16'hbb;
    test_vecs[7][15:8] = 16'hff;  test_vecs[7][7:0] = 16'h00;
    
  end
  initial {i0, i1} = 0;
  prefixAdder PA_0 (i0, i1, o);
  initial begin
    #6 for(i=0;i<`TESTVECS;i=i+1)
      begin #10 {i0, i1}=test_vecs[i]; end
    #100 $finish;
  end
endmodule

prefixAdder.vcd
$date
	Tue Jan 12 14:07:23 2021
$end
$version
	Icarus Verilog
$end
$timescale
	100ps
$end
$scope module tb $end
$var wire 9 ! o [8:0] $end
$var reg 1 " clk $end
$var reg 8 # i0 [7:0] $end
$var reg 8 $ i1 [7:0] $end
$var reg 1 % reset $end
$var integer 32 & i [31:0] $end
$scope module PA_0 $end
$var wire 8 ' a [7:0] $end
$var wire 8 ( b [7:0] $end
$var wire 9 ) sum [8:0] $end
$var wire 9 * s [8:0] $end
$var wire 16 + p [15:0] $end
$var wire 16 , g [15:0] $end
$var wire 1 - cp59 $end
$var wire 1 . cp513 $end
$var wire 1 / cp415 $end
$var wire 1 0 cp411 $end
$var wire 1 1 cp37 $end
$var wire 1 2 cp36 $end
$var wire 1 3 cp35 $end
$var wire 1 4 cp34 $end
$var wire 1 5 cp315 $end
$var wire 1 6 cp27 $end
$var wire 1 7 cp23 $end
$var wire 1 8 cp22 $end
$var wire 1 9 cp215 $end
$var wire 1 : cp211 $end
$var wire 16 ; cp1 [15:0] $end
$var wire 1 < cg59 $end
$var wire 1 = cg513 $end
$var wire 1 > cg415 $end
$var wire 1 ? cg411 $end
$var wire 1 @ cg37 $end
$var wire 1 A cg36 $end
$var wire 1 B cg35 $end
$var wire 1 C cg34 $end
$var wire 1 D cg315 $end
$var wire 1 E cg27 $end
$var wire 1 F cg23 $end
$var wire 1 G cg22 $end
$var wire 1 H cg215 $end
$var wire 1 I cg211 $end
$var wire 16 J cg1 [15:0] $end
$scope module a2 $end
$var wire 1 K i0 $end
$var wire 1 L i1 $end
$var wire 1 M o2 $end
$upscope $end
$scope module and2_g1 $end
$var wire 1 N i0 $end
$var wire 1 O i1 $end
$var wire 1 P o2 $end
$upscope $end
$scope module and2_g2 $end
$var wire 1 Q i0 $end
$var wire 1 R i1 $end
$var wire 1 S o2 $end
$upscope $end
$scope module and2_g3 $end
$var wire 1 T i0 $end
$var wire 1 U i1 $end
$var wire 1 V o2 $end
$upscope $end
$scope module and2_g4 $end
$var wire 1 W i0 $end
$var wire 1 X i1 $end
$var wire 1 Y o2 $end
$upscope $end
$scope module and2_g5 $end
$var wire 1 Z i0 $end
$var wire 1 [ i1 $end
$var wire 1 \ o2 $end
$upscope $end
$scope module and2_g6 $end
$var wire 1 ] i0 $end
$var wire 1 ^ i1 $end
$var wire 1 _ o2 $end
$upscope $end
$scope module and2_g7 $end
$var wire 1 ` i0 $end
$var wire 1 a i1 $end
$var wire 1 b o2 $end
$upscope $end
$scope module and_or_cg1_1 $end
$var wire 1 c a $end
$var wire 1 d b $end
$var wire 1 e c $end
$var wire 1 f x $end
$var wire 1 g y $end
$var wire 1 h t $end
$var wire 1 i e $end
$var wire 1 j d $end
$scope module and2_d $end
$var wire 1 c i0 $end
$var wire 1 d i1 $end
$var wire 1 h o2 $end
$upscope $end
$scope module and2_e $end
$var wire 1 f i0 $end
$var wire 1 g i1 $end
$var wire 1 i o2 $end
$upscope $end
$scope module or2_d $end
$var wire 1 h i0 $end
$var wire 1 e i1 $end
$var wire 1 j o3 $end
$upscope $end
$upscope $end
$scope module and_or_cg1_3 $end
$var wire 1 k a $end
$var wire 1 l b $end
$var wire 1 m c $end
$var wire 1 n x $end
$var wire 1 o y $end
$var wire 1 p t $end
$var wire 1 q e $end
$var wire 1 r d $end
$scope module and2_d $end
$var wire 1 k i0 $end
$var wire 1 l i1 $end
$var wire 1 p o2 $end
$upscope $end
$scope module and2_e $end
$var wire 1 n i0 $end
$var wire 1 o i1 $end
$var wire 1 q o2 $end
$upscope $end
$scope module or2_d $end
$var wire 1 p i0 $end
$var wire 1 m i1 $end
$var wire 1 r o3 $end
$upscope $end
$upscope $end
$scope module and_or_cg1_5 $end
$var wire 1 s a $end
$var wire 1 t b $end
$var wire 1 u c $end
$var wire 1 v x $end
$var wire 1 w y $end
$var wire 1 x t $end
$var wire 1 y e $end
$var wire 1 z d $end
$scope module and2_d $end
$var wire 1 s i0 $end
$var wire 1 t i1 $end
$var wire 1 x o2 $end
$upscope $end
$scope module and2_e $end
$var wire 1 v i0 $end
$var wire 1 w i1 $end
$var wire 1 y o2 $end
$upscope $end
$scope module or2_d $end
$var wire 1 x i0 $end
$var wire 1 u i1 $end
$var wire 1 z o3 $end
$upscope $end
$upscope $end
$scope module and_or_cg1_7 $end
$var wire 1 { a $end
$var wire 1 | b $end
$var wire 1 } c $end
$var wire 1 ~ x $end
$var wire 1 !" y $end
$var wire 1 "" t $end
$var wire 1 #" e $end
$var wire 1 $" d $end
$scope module and2_d $end
$var wire 1 { i0 $end
$var wire 1 | i1 $end
$var wire 1 "" o2 $end
$upscope $end
$scope module and2_e $end
$var wire 1 ~ i0 $end
$var wire 1 !" i1 $end
$var wire 1 #" o2 $end
$upscope $end
$scope module or2_d $end
$var wire 1 "" i0 $end
$var wire 1 } i1 $end
$var wire 1 $" o3 $end
$upscope $end
$upscope $end
$scope module and_or_cg2_11 $end
$var wire 1 %" a $end
$var wire 1 &" b $end
$var wire 1 '" c $end
$var wire 1 (" x $end
$var wire 1 )" y $end
$var wire 1 *" t $end
$var wire 1 : e $end
$var wire 1 I d $end
$scope module and2_d $end
$var wire 1 %" i0 $end
$var wire 1 &" i1 $end
$var wire 1 *" o2 $end
$upscope $end
$scope module and2_e $end
$var wire 1 (" i0 $end
$var wire 1 )" i1 $end
$var wire 1 : o2 $end
$upscope $end
$scope module or2_d $end
$var wire 1 *" i0 $end
$var wire 1 '" i1 $end
$var wire 1 I o3 $end
$upscope $end
$upscope $end
$scope module and_or_cg2_15 $end
$var wire 1 +" a $end
$var wire 1 ," b $end
$var wire 1 -" c $end
$var wire 1 ." x $end
$var wire 1 /" y $end
$var wire 1 0" t $end
$var wire 1 9 e $end
$var wire 1 H d $end
$scope module and2_d $end
$var wire 1 +" i0 $end
$var wire 1 ," i1 $end
$var wire 1 0" o2 $end
$upscope $end
$scope module and2_e $end
$var wire 1 ." i0 $end
$var wire 1 /" i1 $end
$var wire 1 9 o2 $end
$upscope $end
$scope module or2_d $end
$var wire 1 0" i0 $end
$var wire 1 -" i1 $end
$var wire 1 H o3 $end
$upscope $end
$upscope $end
$scope module and_or_cg2_2 $end
$var wire 1 1" a $end
$var wire 1 2" b $end
$var wire 1 3" c $end
$var wire 1 4" x $end
$var wire 1 5" y $end
$var wire 1 6" t $end
$var wire 1 8 e $end
$var wire 1 G d $end
$scope module and2_d $end
$var wire 1 1" i0 $end
$var wire 1 2" i1 $end
$var wire 1 6" o2 $end
$upscope $end
$scope module and2_e $end
$var wire 1 4" i0 $end
$var wire 1 5" i1 $end
$var wire 1 8 o2 $end
$upscope $end
$scope module or2_d $end
$var wire 1 6" i0 $end
$var wire 1 3" i1 $end
$var wire 1 G o3 $end
$upscope $end
$upscope $end
$scope module and_or_cg2_3 $end
$var wire 1 7" a $end
$var wire 1 8" b $end
$var wire 1 9" c $end
$var wire 1 :" x $end
$var wire 1 ;" y $end
$var wire 1 <" t $end
$var wire 1 7 e $end
$var wire 1 F d $end
$scope module and2_d $end
$var wire 1 7" i0 $end
$var wire 1 8" i1 $end
$var wire 1 <" o2 $end
$upscope $end
$scope module and2_e $end
$var wire 1 :" i0 $end
$var wire 1 ;" i1 $end
$var wire 1 7 o2 $end
$upscope $end
$scope module or2_d $end
$var wire 1 <" i0 $end
$var wire 1 9" i1 $end
$var wire 1 F o3 $end
$upscope $end
$upscope $end
$scope module and_or_cg2_7 $end
$var wire 1 =" a $end
$var wire 1 >" b $end
$var wire 1 ?" c $end
$var wire 1 @" x $end
$var wire 1 A" y $end
$var wire 1 B" t $end
$var wire 1 6 e $end
$var wire 1 E d $end
$scope module and2_d $end
$var wire 1 =" i0 $end
$var wire 1 >" i1 $end
$var wire 1 B" o2 $end
$upscope $end
$scope module and2_e $end
$var wire 1 @" i0 $end
$var wire 1 A" i1 $end
$var wire 1 6 o2 $end
$upscope $end
$scope module or2_d $end
$var wire 1 B" i0 $end
$var wire 1 ?" i1 $end
$var wire 1 E o3 $end
$upscope $end
$upscope $end
$scope module and_or_cg3_15 $end
$var wire 1 9 a $end
$var wire 1 I b $end
$var wire 1 H c $end
$var wire 1 9 x $end
$var wire 1 : y $end
$var wire 1 C" t $end
$var wire 1 5 e $end
$var wire 1 D d $end
$scope module and2_d $end
$var wire 1 9 i0 $end
$var wire 1 I i1 $end
$var wire 1 C" o2 $end
$upscope $end
$scope module and2_e $end
$var wire 1 9 i0 $end
$var wire 1 : i1 $end
$var wire 1 5 o2 $end
$upscope $end
$scope module or2_d $end
$var wire 1 C" i0 $end
$var wire 1 H i1 $end
$var wire 1 D o3 $end
$upscope $end
$upscope $end
$scope module and_or_cg3_4 $end
$var wire 1 D" a $end
$var wire 1 F b $end
$var wire 1 E" c $end
$var wire 1 F" x $end
$var wire 1 7 y $end
$var wire 1 G" t $end
$var wire 1 4 e $end
$var wire 1 C d $end
$scope module and2_d $end
$var wire 1 D" i0 $end
$var wire 1 F i1 $end
$var wire 1 G" o2 $end
$upscope $end
$scope module and2_e $end
$var wire 1 F" i0 $end
$var wire 1 7 i1 $end
$var wire 1 4 o2 $end
$upscope $end
$scope module or2_d $end
$var wire 1 G" i0 $end
$var wire 1 E" i1 $end
$var wire 1 C o3 $end
$upscope $end
$upscope $end
$scope module and_or_cg3_5 $end
$var wire 1 H" a $end
$var wire 1 F b $end
$var wire 1 I" c $end
$var wire 1 J" x $end
$var wire 1 7 y $end
$var wire 1 K" t $end
$var wire 1 3 e $end
$var wire 1 B d $end
$scope module and2_d $end
$var wire 1 H" i0 $end
$var wire 1 F i1 $end
$var wire 1 K" o2 $end
$upscope $end
$scope module and2_e $end
$var wire 1 J" i0 $end
$var wire 1 7 i1 $end
$var wire 1 3 o2 $end
$upscope $end
$scope module or2_d $end
$var wire 1 K" i0 $end
$var wire 1 I" i1 $end
$var wire 1 B o3 $end
$upscope $end
$upscope $end
$scope module and_or_cg3_6 $end
$var wire 1 L" a $end
$var wire 1 B b $end
$var wire 1 M" c $end
$var wire 1 N" x $end
$var wire 1 3 y $end
$var wire 1 O" t $end
$var wire 1 2 e $end
$var wire 1 A d $end
$scope module and2_d $end
$var wire 1 L" i0 $end
$var wire 1 B i1 $end
$var wire 1 O" o2 $end
$upscope $end
$scope module and2_e $end
$var wire 1 N" i0 $end
$var wire 1 3 i1 $end
$var wire 1 2 o2 $end
$upscope $end
$scope module or2_d $end
$var wire 1 O" i0 $end
$var wire 1 M" i1 $end
$var wire 1 A o3 $end
$upscope $end
$upscope $end
$scope module and_or_cg3_7 $end
$var wire 1 6 a $end
$var wire 1 F b $end
$var wire 1 E c $end
$var wire 1 6 x $end
$var wire 1 7 y $end
$var wire 1 P" t $end
$var wire 1 1 e $end
$var wire 1 @ d $end
$scope module and2_d $end
$var wire 1 6 i0 $end
$var wire 1 F i1 $end
$var wire 1 P" o2 $end
$upscope $end
$scope module and2_e $end
$var wire 1 6 i0 $end
$var wire 1 7 i1 $end
$var wire 1 1 o2 $end
$upscope $end
$scope module or2_d $end
$var wire 1 P" i0 $end
$var wire 1 E i1 $end
$var wire 1 @ o3 $end
$upscope $end
$upscope $end
$scope module and_or_cg4_11 $end
$var wire 1 : a $end
$var wire 1 @ b $end
$var wire 1 I c $end
$var wire 1 : x $end
$var wire 1 1 y $end
$var wire 1 Q" t $end
$var wire 1 0 e $end
$var wire 1 ? d $end
$scope module and2_d $end
$var wire 1 : i0 $end
$var wire 1 @ i1 $end
$var wire 1 Q" o2 $end
$upscope $end
$scope module and2_e $end
$var wire 1 : i0 $end
$var wire 1 1 i1 $end
$var wire 1 0 o2 $end
$upscope $end
$scope module or2_d $end
$var wire 1 Q" i0 $end
$var wire 1 I i1 $end
$var wire 1 ? o3 $end
$upscope $end
$upscope $end
$scope module and_or_cg4_15 $end
$var wire 1 5 a $end
$var wire 1 @ b $end
$var wire 1 D c $end
$var wire 1 5 x $end
$var wire 1 1 y $end
$var wire 1 R" t $end
$var wire 1 / e $end
$var wire 1 > d $end
$scope module and2_d $end
$var wire 1 5 i0 $end
$var wire 1 @ i1 $end
$var wire 1 R" o2 $end
$upscope $end
$scope module and2_e $end
$var wire 1 5 i0 $end
$var wire 1 1 i1 $end
$var wire 1 / o2 $end
$upscope $end
$scope module or2_d $end
$var wire 1 R" i0 $end
$var wire 1 D i1 $end
$var wire 1 > o3 $end
$upscope $end
$upscope $end
$scope module and_or_cg5_13 $end
$var wire 1 S" a $end
$var wire 1 ? b $end
$var wire 1 T" c $end
$var wire 1 U" x $end
$var wire 1 0 y $end
$var wire 1 V" t $end
$var wire 1 . e $end
$var wire 1 = d $end
$scope module and2_d $end
$var wire 1 S" i0 $end
$var wire 1 ? i1 $end
$var wire 1 V" o2 $end
$upscope $end
$scope module and2_e $end
$var wire 1 U" i0 $end
$var wire 1 0 i1 $end
$var wire 1 . o2 $end
$upscope $end
$scope module or2_d $end
$var wire 1 V" i0 $end
$var wire 1 T" i1 $end
$var wire 1 = o3 $end
$upscope $end
$upscope $end
$scope module and_or_cg5_9 $end
$var wire 1 W" a $end
$var wire 1 @ b $end
$var wire 1 X" c $end
$var wire 1 Y" x $end
$var wire 1 1 y $end
$var wire 1 Z" t $end
$var wire 1 - e $end
$var wire 1 < d $end
$scope module and2_d $end
$var wire 1 W" i0 $end
$var wire 1 @ i1 $end
$var wire 1 Z" o2 $end
$upscope $end
$scope module and2_e $end
$var wire 1 Y" i0 $end
$var wire 1 1 i1 $end
$var wire 1 - o2 $end
$upscope $end
$scope module or2_d $end
$var wire 1 Z" i0 $end
$var wire 1 X" i1 $end
$var wire 1 < o3 $end
$upscope $end
$upscope $end
$scope module xor2_p0 $end
$var wire 1 [" i0 $end
$var wire 1 \" i1 $end
$var wire 1 ]" o4 $end
$upscope $end
$scope module xor2_p1 $end
$var wire 1 ^" i0 $end
$var wire 1 _" i1 $end
$var wire 1 `" o4 $end
$upscope $end
$scope module xor2_p2 $end
$var wire 1 a" i0 $end
$var wire 1 b" i1 $end
$var wire 1 c" o4 $end
$upscope $end
$scope module xor2_p3 $end
$var wire 1 d" i0 $end
$var wire 1 e" i1 $end
$var wire 1 f" o4 $end
$upscope $end
$scope module xor2_p5 $end
$var wire 1 g" i0 $end
$var wire 1 h" i1 $end
$var wire 1 i" o4 $end
$upscope $end
$scope module xor2_p6 $end
$var wire 1 j" i0 $end
$var wire 1 k" i1 $end
$var wire 1 l" o4 $end
$upscope $end
$scope module xor2_p7 $end
$var wire 1 m" i0 $end
$var wire 1 n" i1 $end
$var wire 1 o" o4 $end
$upscope $end
$scope module xor2_s1 $end
$var wire 1 p" i0 $end
$var wire 1 q" i1 $end
$var wire 1 r" o4 $end
$upscope $end
$scope module xor2_s2 $end
$var wire 1 s" i0 $end
$var wire 1 t" i1 $end
$var wire 1 u" o4 $end
$upscope $end
$scope module xor2_s3 $end
$var wire 1 v" i0 $end
$var wire 1 G i1 $end
$var wire 1 w" o4 $end
$upscope $end
$scope module xor2_s4 $end
$var wire 1 x" i0 $end
$var wire 1 F i1 $end
$var wire 1 y" o4 $end
$upscope $end
$scope module xor2_s5 $end
$var wire 1 z" i0 $end
$var wire 1 C i1 $end
$var wire 1 {" o4 $end
$upscope $end
$scope module xor2_s6 $end
$var wire 1 |" i0 $end
$var wire 1 B i1 $end
$var wire 1 }" o4 $end
$upscope $end
$scope module xor2_s7 $end
$var wire 1 ~" i0 $end
$var wire 1 A i1 $end
$var wire 1 !# o4 $end
$upscope $end
$scope module xpr2_p4 $end
$var wire 1 "# i0 $end
$var wire 1 ## i1 $end
$var wire 1 $# o4 $end
$upscope $end
$upscope $end
$upscope $end
$enddefinitions $end
#0
$dumpvars
0$#
0##
0"#
0!#
0~"
0}"
0|"
0{"
0z"
0y"
0x"
0w"
0v"
0u"
0t"
0s"
0r"
0q"
0p"
0o"
0n"
0m"
0l"
0k"
0j"
0i"
0h"
0g"
0f"
0e"
0d"
0c"
0b"
0a"
0`"
0_"
0^"
0]"
0\"
0["
0Z"
zY"
zX"
zW"
xV"
zU"
zT"
zS"
0R"
0Q"
0P"
0O"
0N"
0M"
0L"
0K"
0J"
0I"
0H"
0G"
0F"
0E"
0D"
xC"
0B"
0A"
0@"
0?"
0>"
0="
0<"
0;"
0:"
09"
08"
07"
06"
05"
04"
03"
02"
01"
x0"
z/"
z."
z-"
z,"
z+"
x*"
z)"
z("
z'"
z&"
z%"
0$"
0#"
0""
0!"
0~
0}
0|
0{
0z
0y
0x
0w
0v
0u
0t
0s
0r
0q
0p
0o
0n
0m
0l
0k
0j
0i
0h
0g
0f
0e
0d
0c
0b
0a
0`
0_
0^
0]
0\
0[
0Z
0Y
0X
0W
0V
0U
0T
0S
0R
0Q
0P
0O
0N
0M
0L
0K
bz00000000 J
xI
xH
0G
0F
0E
xD
0C
0B
0A
0@
x?
x>
x=
x<
bz00000000 ;
x:
x9
08
07
06
x5
04
03
02
01
00
0/
0.
0-
bz00000000 ,
bz00000000 +
b0 *
b0 )
b0 (
b0 '
bx &
1%
b0 $
b0 #
0"
b0 !
$end
#50
1"
#60
b0 &
#100
0"
#125
0%
#150
1"
#160
b1 !
b1 )
b1 *
bz00000001 ;
bz00000001 +
1]"
1["
1K
b1 &
b1 #
b1 '
#200
0"
#250
1"
#260
1r"
1q"
b10 !
b10 )
b10 *
bz00000000 ;
1g
1d
bz00000001 J
bz00000000 +
0]"
bz00000001 ,
1M
1\"
1L
b10 &
b1 $
b1 (
#300
0"
#350
1"
#360
1A
1O"
xQ"
xR"
xZ"
1C
1B
1@
1G"
1K"
1P"
x.
1F
1G
12
x0
x/
x-
1<"
16"
14
13
11
18
1t"
18"
12"
17
16
1;"
15"
bz00000011 J
1j
1:"
17"
1J"
1H"
1A"
1@"
1="
0r"
1i
1h
0u"
14"
11"
0w"
1q
0y"
1F"
1D"
0{"
1y
0}"
1N"
1L"
b100000000 !
b100000000 )
b100000000 *
0!#
1#"
1p"
1f
1c
1s"
1o
1v"
1n
1k
1x"
1w
1z"
1v
1s
1|"
1!"
bz11111110 ;
1~"
1~
1{
1`"
1c"
1f"
1$#
1i"
1l"
bz11111110 +
1o"
1^"
1N
1a"
1Q
1d"
1T
1"#
1W
1g"
1Z
1j"
1]
1m"
1`
b11 &
b11111111 #
b11111111 '
#400
0"
#450
1"
#460
0.
00
0/
0-
0P"
01
07
0<"
03
0K"
06
1E
0;"
05"
08
06"
0:"
07"
19"
04
0G"
0J"
0H"
0A"
1I"
1>"
02
0O"
0@"
0="
1?"
1r"
0i
0h
1u"
04"
01"
13"
1w"
0q
1r
1y"
0F"
0D"
1E"
1{"
0y
1z
1}"
0N"
0L"
1M"
b111111110 !
b111111110 )
b111111110 *
1!#
0#"
1$"
0p"
0f
0c
1e
0s"
0o
1l
0v"
0n
0k
1m
0x"
0w
1t
0z"
0v
0s
1u
0|"
0!"
bz00000000 ;
1|
bz11111111 J
0~"
0~
0{
1}
0`"
1P
0c"
1S
0f"
1V
0$#
1Y
0i"
1\
0l"
1_
bz00000000 +
0o"
bz11111111 ,
1b
1_"
1O
1b"
1R
1e"
1U
1##
1X
1h"
1[
1k"
1^
1n"
1a
b100 &
b11111111 $
b11111111 (
#500
0"
#550
1"
#560
1{"
1!#
1w"
1G"
1C
1O"
1A
0r"
16"
1G
0y"
1F"
1D"
0E"
0}"
1N"
1L"
0M"
0q"
0u"
14"
11"
03"
1x"
1w
0t
1|"
1!"
0|
b110101001 !
b110101001 )
b110101001 *
0g
0d
1s"
1o
bz01010101 ;
0l
bz10101010 J
1$#
0Y
1l"
0_
1]"
0M
bz01010101 +
1c"
bz10101010 ,
0S
0"#
0W
0j"
0]
0\"
0L
0b"
0R
b101 &
b10101111 #
b10101111 '
b11111010 $
b11111010 (
#600
0"
#650
1"
#660
0G
0F
06"
09"
0G"
0O"
1r"
0t"
08"
02"
0u"
04"
01"
1w"
0r
0y"
0F"
0D"
1E"
1}"
0N"
0L"
1M"
1q"
0j
0s"
0o
1v"
1n
1k
0m
0x"
0w
1t
0|"
0!"
1|
b111101010 !
b111101010 )
b111101010 *
bz00000000 ;
1g
1d
bz11110001 J
0e
0c"
1f"
0V
0$#
1Y
0l"
1_
bz00001000 +
0]"
1M
bz11110001 ,
0P
0^"
0N
0a"
0Q
0d"
0T
1"#
1W
1j"
1]
1\"
1L
0_"
0O
b110 &
b11110001 #
b11110001 '
b11111001 $
b11111001 (
#700
0"
#750
1"
#760
1G"
1K"
1F
1B
1!#
19"
1C
1J"
1H"
1A"
0I"
0>"
1O"
1A
0q"
1u"
14"
11"
0w"
1r
0y"
1F"
1D"
0E"
0{"
1y
0z
1r"
0}"
1N"
1L"
0M"
b110000111 !
b110000111 )
b110000111 *
0g
0d
1s"
1o
0v"
0n
0k
1m
1x"
1w
0t
1z"
1v
1s
0u
1p"
1f
1c
1|"
1!"
bz01110101 ;
0|
bz10001000 J
1]"
0M
1c"
0f"
1V
1$#
0Y
1i"
0\
1`"
bz01110111 +
1l"
bz10001000 ,
0_
0["
0K
1a"
1Q
1d"
1T
0"#
0W
0g"
0Z
1_"
1O
0k"
0^
b111 &
b11001100 #
b11001100 '
b10111011 $
b10111011 (
#800
0"
#850
1"
#860
0A
1{"
0O"
1}"
0C
0B
0Q"
0R"
0Z"
0G"
0K"
1y"
0@
0F
16
0E
1:"
17"
09"
1@"
1="
0?"
1w"
1q
0r
b11111111 !
b11111111 )
b11111111 *
1!#
bz11111101 ;
1#"
bz00000000 J
0$"
1v"
1n
1k
0m
1~"
1~
1{
0}
1f"
0V
bz11111111 +
1o"
bz00000000 ,
0b
1["
1K
1^"
1N
1"#
1W
1g"
1Z
0\"
0L
0_"
0O
0e"
0U
0##
0X
0h"
0[
0n"
0a
b1000 &
b11111111 #
b11111111 '
b0 $
b0 (
